pymfoil/__init__.py
pymfoil/mfoil.py
pymfoil/mfoil_notex.py
pymfoil-0.1.0.dist-info/licenses/LICENSE
pymfoil-0.1.0.dist-info/METADATA
pymfoil-0.1.0.dist-info/WHEEL
pymfoil-0.1.0.dist-info/top_level.txt
pymfoil-0.1.0.dist-info/RECORD
