Metadata-Version: 2.4
Name: pymfoil
Version: 0.1.0
Summary: A Python package for aerodynamic airfoil analysis based on mfoil.
Author-email: "N. Papadakis" <npapnet@gmail.com>
License: MIT License
Project-URL: Homepage, https://github.com/npapnet/pymfoil
Project-URL: Bug Tracker, https://github.com/npapnet/pymfoil/issues
Project-URL: Repository, https://github.com/npapnet/pymfoil
Project-URL: Documentation, https://npapnet.github.io/pymfoil/
Project-URL: Source, https://github.com/npapnet/pymfoil
Keywords: airfoil,aerodynamics,naca,engineering
Classifier: Development Status :: 3 - Alpha
Classifier: Intended Audience :: Science/Research
Classifier: License :: OSI Approved :: MIT License
Classifier: Operating System :: OS Independent
Classifier: Programming Language :: Python :: 3
Classifier: Programming Language :: Python :: 3.8
Classifier: Programming Language :: Python :: 3.9
Classifier: Programming Language :: Python :: 3.10
Classifier: Programming Language :: Python :: 3.11
Classifier: Topic :: Scientific/Engineering
Requires-Python: >=3.8
License-File: LICENSE
Requires-Dist: numpy>=1.21.0
Requires-Dist: matplotlib>=3.5.0
Requires-Dist: scipy
Provides-Extra: docs
Requires-Dist: sphinx; extra == "docs"
Requires-Dist: sphinx-rtd-theme; extra == "docs"
Provides-Extra: test
Requires-Dist: pytest; extra == "test"
Dynamic: license-file
